{
    "swagger": "2.0",
    "info": {
        "description": "API endpoints for registering users.",
        "title": "Playtorium Auth API",
        "contact": {},
        "version": "1.0"
    },
    "host": "localhost:8080",
    "basePath": "/",
    "paths": {
        "/register": {
            "post": {
                "description": "Creates a new user account with hashed password.",
                "consumes": [
                    "application/json"
                ],
                "produces": [
                    "application/json"
                ],
                "tags": [
                    "Auth"
                ],
                "summary": "Register a new user",
                "parameters": [
                    {
                        "description": "Register payload",
                        "name": "register",
                        "in": "body",
                        "required": true,
                        "schema": {
                            "$ref": "#/definitions/handlers.RegisterRequest"
                        }
                    }
                ],
                "responses": {
                    "201": {
                        "description": "Created",
                        "schema": {
                            "$ref": "#/definitions/handlers.RegisterResponse"
                        }
                    },
                    "400": {
                        "description": "Bad Request",
                        "schema": {
                            "$ref": "#/definitions/handlers.ErrorResponse"
                        }
                    },
                    "500": {
                        "description": "Internal Server Error",
                        "schema": {
                            "$ref": "#/definitions/handlers.ErrorResponse"
                        }
                    }
                }
            }
        },
        "/users": {
            "get": {
                "description": "Returns a list of all registered users.",
                "produces": [
                    "application/json"
                ],
                "tags": [
                    "Users"
                ],
                "summary": "Get all users",
                "responses": {
                    "200": {
                        "description": "OK",
                        "schema": {
                            "$ref": "#/definitions/handlers.UsersResponse"
                        }
                    },
                    "500": {
                        "description": "Internal Server Error",
                        "schema": {
                            "$ref": "#/definitions/handlers.ErrorResponse"
                        }
                    }
                }
            }
        }
    },
    "definitions": {
        "handlers.ErrorResponse": {
            "type": "object",
            "properties": {
                "error": {
                    "type": "string"
                }
            }
        },
        "handlers.RegisterRequest": {
            "type": "object",
            "properties": {
                "email": {
                    "type": "string"
                },
                "first_name": {
                    "type": "string"
                },
                "last_name": {
                    "type": "string"
                },
                "password": {
                    "type": "string"
                }
            }
        },
        "handlers.RegisterResponse": {
            "type": "object",
            "properties": {
                "Message": {
                    "type": "string"
                },
                "user": {
                    "$ref": "#/definitions/handlers.RegisterUserPayload"
                }
            }
        },
        "handlers.RegisterUserPayload": {
            "type": "object",
            "properties": {
                "email": {
                    "type": "string"
                },
                "first_name": {
                    "type": "string"
                },
                "id": {
                    "type": "string"
                },
                "last_name": {
                    "type": "string"
                }
            }
        },
        "handlers.UsersResponse": {
            "type": "object",
            "properties": {
                "users": {
                    "type": "array",
                    "items": {
                        "$ref": "#/definitions/models.User"
                    }
                }
            }
        },
        "models.User": {
            "type": "object",
            "properties": {
                "created_at": {
                    "type": "string"
                },
                "email": {
                    "type": "string"
                },
                "first_name": {
                    "type": "string"
                },
                "id": {
                    "type": "string"
                },
                "last_name": {
                    "type": "string"
                }
            }
        }
    }
}